ml_exp/__init__.py
ml_exp/controller/__init__.py
ml_exp/controller/console.py
ml_exp/ml_exp.py
ml_exp/model/ab_test_results.py
ml_exp/model/ml_model.py
ml_exp/model/report.py
ml_exp/repository/ab_test_repository.py
ml_exp/repository/general_model_repository.py
ml_exp/repository/interfaces/data_file_repository.py
ml_exp/repository/interfaces/model_repository.py
ml_exp/repository/pandas_data_file_repository.py
ml_exp/repository/sklearn_model_repository.py
ml_exp/service/ab_pipeline_service.py
ml_exp/service/experimental_pipeline_service.py
ml_exp/service/generate_score_service.py
ml_exp/service/load_model_service.py
ml_exp/service/load_test_data_service.py
ml_exp/service/prepare_context_service.py
ml_exp/service/report_generator_service.py
ml_exp/templates/report.html
ml_exp/utils/log_config.py
ml_experimentation-0.0.1.dist-info/LICENSE
ml_experimentation-0.0.1.dist-info/METADATA
ml_experimentation-0.0.1.dist-info/WHEEL
ml_experimentation-0.0.1.dist-info/entry_points.txt
ml_experimentation-0.0.1.dist-info/RECORD
