Metadata-Version: 2.3
Name: ml_experimentation
Version: 0.0.1
Summary: 
Author: iuryrosal
Author-email: iuryrosal@gmail.com
Requires-Python: >=3.10,<4.0
Classifier: Programming Language :: Python :: 3
Classifier: Programming Language :: Python :: 3.10
Classifier: Programming Language :: Python :: 3.11
Classifier: Programming Language :: Python :: 3.12
Classifier: Programming Language :: Python :: 3.13
Requires-Dist: jinja2 (>=3.1.6,<4.0.0)
Requires-Dist: mlflow (>=3.1.4,<4.0.0)
Requires-Dist: onnxruntime (>=1.22.0,<2.0.0)
Requires-Dist: pandas (>=2.2.3,<3.0.0)
Requires-Dist: pydantic (>=2.11.7,<3.0.0)
Requires-Dist: pytest (>=8.4.0,<9.0.0)
Requires-Dist: scikit-learn (>=1.6.1,<2.0.0)
Requires-Dist: skl2onnx (>=1.19.1,<2.0.0)
Requires-Dist: statsmodels (>=0.14.4,<0.15.0)
